{
   "@context" : "https://gbv.github.io/jskos/context.json",
   "altLabel" : {
      "en" : [
         "Thema",
         "Subject Category Scheme for a Global Book Trade"
      ]
   },
   "languages" : [
      "ar",
      "en",
      "fr",
      "de",
      "it",
      "ja",
      "no",
      "ru",
      "es",
      "sv"
   ],
   "prefLabel" : {
      "en" : "Subject Category Scheme for a Global Book Trade"
   },
   "subject" : [
      {
         "prefLabel" : {
            "en" : "book trade"
         },
         "uri" : "http://eurovoc.europa.eu/1392"
      },
      {
         "uri" : "http://dewey.info/class/002/e23/"
      }
   ],
   "type" : [
      "http://www.w3.org/2004/02/skos/core#ConceptScheme",
      "http://w3id.org/nkos/nkostype#classification_schema"
   ],
   "uri" : "http://bartoc.org/en/node/1043",
   "url" : "http://www.editeur.org/151/thema/en/welcome-to-thema/"
}