{
   "@context" : "https://gbv.github.io/jskos/context.json",
   "languages" : [
      "en"
   ],
   "prefLabel" : {
      "en" : "Thesaurus of Musical Instruments"
   },
   "subject" : [
      {
         "prefLabel" : {
            "en" : "musical instrument"
         },
         "uri" : "http://eurovoc.europa.eu/1458"
      },
      {
         "uri" : "http://dewey.info/class/784/e23/"
      }
   ],
   "type" : [
      "http://www.w3.org/2004/02/skos/core#ConceptScheme",
      "http://w3id.org/nkos/nkostype#thesaurus"
   ],
   "uri" : "http://bartoc.org/en/node/116",
   "url" : "http://alteriseculo.com/instruments/"
}