{
   "@context" : "https://gbv.github.io/jskos/context.json",
   "altLabel" : {
      "und" : [
         "AODN Instrument Vocabulary",
         "AODN Instruments"
      ]
   },
   "languages" : [
      "en"
   ],
   "prefLabel" : {
      "und" : "AODN Instruments"
   },
   "subject" : [
      {
         "prefLabel" : {
            "en" : "oceanography"
         },
         "uri" : "http://eurovoc.europa.eu/2114"
      },
      {
         "uri" : "http://dewey.info/class/551/e23/"
      }
   ],
   "type" : [
      "http://www.w3.org/2004/02/skos/core#ConceptScheme",
      "http://w3id.org/nkos/nkostype#list"
   ],
   "uri" : "http://bartoc.org/en/node/1694",
   "url" : "https://vocabs.ands.org.au/aodn-instrument-vocabulary"
}