{
   "@context" : "https://gbv.github.io/jskos/context.json",
   "altLabel" : {
      "en" : [
         "KVINNSAM Subject headings"
      ],
      "und" : [
         "KVINNSAM Ämnesordslista"
      ]
   },
   "creator" : [
      {
         "uri" : "http://viaf.org/viaf/143581110"
      }
   ],
   "languages" : [
      "en",
      "sv"
   ],
   "prefLabel" : {
      "en" : "KVINNSAM Subject headings"
   },
   "subject" : [
      {
         "prefLabel" : {
            "en" : "man"
         },
         "uri" : "http://eurovoc.europa.eu/5281"
      },
      {
         "prefLabel" : {
            "en" : "Northern Europe"
         },
         "uri" : "http://eurovoc.europa.eu/911"
      },
      {
         "prefLabel" : {
            "en" : "woman"
         },
         "uri" : "http://eurovoc.europa.eu/5280"
      },
      {
         "uri" : "http://dewey.info/class/300/e23/"
      },
      {
         "uri" : "http://dewey.info/class/948/e23/"
      }
   ],
   "type" : [
      "http://www.w3.org/2004/02/skos/core#ConceptScheme",
      "http://w3id.org/nkos/nkostype#subject_heading_scheme"
   ],
   "uri" : "http://bartoc.org/en/node/258",
   "url" : "http://www.ub.gu.se/kvinn/kvinnsam/listor/amnesord.html"
}