{
   "@context" : "https://gbv.github.io/jskos/context.json",
   "altLabel" : {
      "en" : [
         "National Library of Medicine Classification"
      ],
      "und" : [
         "NLM Classification"
      ]
   },
   "creator" : [
      {
         "uri" : "http://viaf.org/viaf/139054940"
      }
   ],
   "identifier" : [
      "http://www.wikidata.org/entity/Q986957"
   ],
   "languages" : [
      "en"
   ],
   "prefLabel" : {
      "und" : "NLM Classification"
   },
   "subject" : [
      {
         "prefLabel" : {
            "en" : "medicine"
         },
         "uri" : "http://eurovoc.europa.eu/1852"
      },
      {
         "uri" : "http://dewey.info/class/610/e23/"
      }
   ],
   "type" : [
      "http://www.w3.org/2004/02/skos/core#ConceptScheme",
      "http://w3id.org/nkos/nkostype#classification_schema"
   ],
   "uri" : "http://bartoc.org/en/node/528",
   "url" : "http://www.nlm.nih.gov/class/"
}