{
   "@context" : "https://gbv.github.io/jskos/context.json",
   "languages" : [
      "en"
   ],
   "notation" : [
      "CDAO"
   ],
   "prefLabel" : {
      "en" : "Comparative Data Analysis Ontology",
      "und" : "CDAO"
   },
   "subject" : [
      {
         "prefLabel" : {
            "en" : "life sciences"
         },
         "uri" : "http://eurovoc.europa.eu/3941"
      },
      {
         "uri" : "http://dewey.info/class/005/e23/"
      },
      {
         "uri" : "http://dewey.info/class/576/e23/"
      }
   ],
   "type" : [
      "http://www.w3.org/2004/02/skos/core#ConceptScheme",
      "http://w3id.org/nkos/nkostype#ontology"
   ],
   "uri" : "http://bartoc.org/en/node/565",
   "url" : "http://sourceforge.net/projects/cdao/"
}