{
   "@context" : "https://gbv.github.io/jskos/context.json",
   "altLabel" : {
      "en" : [
         "Classification of General Electoral District",
         "GED07"
      ]
   },
   "creator" : [
      {
         "uri" : "http://viaf.org/viaf/148067905"
      }
   ],
   "languages" : [
      "en"
   ],
   "prefLabel" : {
      "en" : "GED07"
   },
   "subject" : [
      {
         "prefLabel" : {
            "en" : "election"
         },
         "uri" : "http://eurovoc.europa.eu/695"
      },
      {
         "uri" : "http://dewey.info/class/324/e23/"
      }
   ],
   "type" : [
      "http://www.w3.org/2004/02/skos/core#ConceptScheme",
      "http://w3id.org/nkos/nkostype#classification_schema"
   ],
   "uri" : "http://bartoc.org/en/node/797",
   "url" : "http://www.stats.govt.nz/methods/classifications-and-standards/classification-related-stats-standards/general-electoral-district.aspx"
}