{
   "@context" : "https://gbv.github.io/jskos/context.json",
   "languages" : [
      "en"
   ],
   "prefLabel" : {
      "en" : "Pendlebury Library of Music Classification System"
   },
   "subject" : [
      {
         "prefLabel" : {
            "en" : "music"
         },
         "uri" : "http://eurovoc.europa.eu/2023"
      },
      {
         "uri" : "http://dewey.info/class/780/e23/"
      }
   ],
   "type" : [
      "http://www.w3.org/2004/02/skos/core#ConceptScheme",
      "http://w3id.org/nkos/nkostype#classification_schema"
   ],
   "uri" : "http://bartoc.org/en/node/867",
   "url" : "http://pendlebury.mus.cam.ac.uk/library-collections/classification-system"
}