{
   "@context" : "https://gbv.github.io/jskos/context.json",
   "altLabel" : {
      "en" : [
         "Superintendent of Documents Classification System"
      ],
      "und" : [
         "SuDocs Classification System"
      ]
   },
   "creator" : [
      {
         "uri" : "http://viaf.org/viaf/133683268/"
      }
   ],
   "languages" : [
      "en"
   ],
   "prefLabel" : {
      "und" : "SuDocs Classification System"
   },
   "subject" : [
      {
         "prefLabel" : {
            "en" : "United States"
         },
         "uri" : "http://eurovoc.europa.eu/888"
      },
      {
         "prefLabel" : {
            "en" : "government"
         },
         "uri" : "http://eurovoc.europa.eu/1172"
      },
      {
         "uri" : "http://dewey.info/class/320/e23/"
      },
      {
         "uri" : "http://dewey.info/class/973/e23/"
      }
   ],
   "type" : [
      "http://www.w3.org/2004/02/skos/core#ConceptScheme",
      "http://w3id.org/nkos/nkostype#classification_schema"
   ],
   "uri" : "http://bartoc.org/en/node/868",
   "url" : "http://www.library.illinois.edu/doc/researchtools/guides/usfederal/sudoclist.html"
}